README.md
cookietransfer.py
setup.py
cookietransfer.egg-info/PKG-INFO
cookietransfer.egg-info/SOURCES.txt
cookietransfer.egg-info/dependency_links.txt
cookietransfer.egg-info/requires.txt
cookietransfer.egg-info/top_level.txt