Metadata-Version: 1.0
Name: cookietransfer
Version: 0.1.0
Summary: helps cookie transfer between requests session and selenium browser instance with ease
Home-page: https://github.com/terry-lim/cookietransfer
Author: Terry Lim
Author-email: UNKNOWN
License: MIT
Keywords: cookie,session,selenium,requests,chrome,firefox
Platform: UNKNOWN
